MANIFEST.in
VERSION
setup.py
tensorshield.ext.axon.egg-info/PKG-INFO
tensorshield.ext.axon.egg-info/SOURCES.txt
tensorshield.ext.axon.egg-info/dependency_links.txt
tensorshield.ext.axon.egg-info/requires.txt
tensorshield.ext.axon.egg-info/top_level.txt
tensorshield/ext/axon/__init__.py
tensorshield/ext/axon/_apiroute.py
tensorshield/ext/axon/_axon.py
tensorshield/ext/axon/_request.py
tensorshield/ext/axon/_response.py
tensorshield/ext/axon/_router.py
tensorshield/ext/axon/package.json